odoo10_addon_purchase_stock_picking_return_invoicing-10.0.1.0.1-py2.7-nspkg.pth
odoo/addons/purchase_stock_picking_return_invoicing/README.rst
odoo/addons/purchase_stock_picking_return_invoicing/__init__.py
odoo/addons/purchase_stock_picking_return_invoicing/__manifest__.py
odoo/addons/purchase_stock_picking_return_invoicing/i18n/ar.po
odoo/addons/purchase_stock_picking_return_invoicing/i18n/bg.po
odoo/addons/purchase_stock_picking_return_invoicing/i18n/bs.po
odoo/addons/purchase_stock_picking_return_invoicing/i18n/ca.po
odoo/addons/purchase_stock_picking_return_invoicing/i18n/cs.po
odoo/addons/purchase_stock_picking_return_invoicing/i18n/de.po
odoo/addons/purchase_stock_picking_return_invoicing/i18n/el_GR.po
odoo/addons/purchase_stock_picking_return_invoicing/i18n/en_GB.po
odoo/addons/purchase_stock_picking_return_invoicing/i18n/es.po
odoo/addons/purchase_stock_picking_return_invoicing/i18n/es_CR.po
odoo/addons/purchase_stock_picking_return_invoicing/i18n/es_EC.po
odoo/addons/purchase_stock_picking_return_invoicing/i18n/es_ES.po
odoo/addons/purchase_stock_picking_return_invoicing/i18n/es_MX.po
odoo/addons/purchase_stock_picking_return_invoicing/i18n/es_PE.po
odoo/addons/purchase_stock_picking_return_invoicing/i18n/et.po
odoo/addons/purchase_stock_picking_return_invoicing/i18n/fi.po
odoo/addons/purchase_stock_picking_return_invoicing/i18n/fr.po
odoo/addons/purchase_stock_picking_return_invoicing/i18n/fr_CA.po
odoo/addons/purchase_stock_picking_return_invoicing/i18n/fr_CH.po
odoo/addons/purchase_stock_picking_return_invoicing/i18n/fr_FR.po
odoo/addons/purchase_stock_picking_return_invoicing/i18n/gl.po
odoo/addons/purchase_stock_picking_return_invoicing/i18n/hr.po
odoo/addons/purchase_stock_picking_return_invoicing/i18n/hr_HR.po
odoo/addons/purchase_stock_picking_return_invoicing/i18n/hu.po
odoo/addons/purchase_stock_picking_return_invoicing/i18n/id.po
odoo/addons/purchase_stock_picking_return_invoicing/i18n/it.po
odoo10_addon_purchase_stock_picking_return_invoicing-10.0.1.0.1.dist-info/DESCRIPTION.rst
odoo10_addon_purchase_stock_picking_return_invoicing-10.0.1.0.1.dist-info/METADATA
odoo10_addon_purchase_stock_picking_return_invoicing-10.0.1.0.1.dist-info/RECORD
odoo10_addon_purchase_stock_picking_return_invoicing-10.0.1.0.1.dist-info/WHEEL
odoo10_addon_purchase_stock_picking_return_invoicing-10.0.1.0.1.dist-info/metadata.json
odoo10_addon_purchase_stock_picking_return_invoicing-10.0.1.0.1.dist-info/namespace_packages.txt
odoo10_addon_purchase_stock_picking_return_invoicing-10.0.1.0.1.dist-info/top_level.txt
