Metadata-Version: 2.0
Name: odoo10-addon-purchase-stock-picking-return-invoicing
Version: 10.0.1.0.1
Summary: Add an option to refund returned pickings
Home-page: https://github.com/OCA/account-invoicing
Author: Eficent,Tecnativa,Odoo Community Association (OCA)
Author-email: support@odoo-community.org
License: AGPL-3
Platform: UNKNOWN
Classifier: Programming Language :: Python
Classifier: Framework :: Odoo
Classifier: License :: OSI Approved :: GNU Affero General Public License v3
Requires-Python: ~=2.7
Requires-Dist: odoo (<10.1dev,>=10.0)
